ontmont/__init__.py
ontmont/bundle.py
ontmont/cli.py
ontmont/collect.py
ontmont/datatypes.py
ontmont/irs.py
ontmont/plot.py
ontmont/process.py
ontmont/utils.py
ontmont-0.0.8.dist-info/LICENSE
ontmont-0.0.8.dist-info/METADATA
ontmont-0.0.8.dist-info/WHEEL
ontmont-0.0.8.dist-info/entry_points.txt
ontmont-0.0.8.dist-info/top_level.txt
ontmont-0.0.8.dist-info/RECORD
